mysql/__init__.py
mysql/mysql.py
qianqiuvideo/__init__.py
qianqiuvideo/mysql.py
qianqiuvideo/test.py
qianqiuvideo-0.0.9.data/scripts/mysql.py
qianqiuvideo-0.0.9.data/scripts/test.py
qianqiuvideo-0.0.9.dist-info/METADATA
qianqiuvideo-0.0.9.dist-info/WHEEL
qianqiuvideo-0.0.9.dist-info/top_level.txt
qianqiuvideo-0.0.9.dist-info/RECORD
